LICENSE
MANIFEST.in
README.md
setup.py
contents/__init__.py
contents.egg-info/PKG-INFO
contents.egg-info/SOURCES.txt
contents.egg-info/dependency_links.txt
contents.egg-info/entry_points.txt
contents.egg-info/top_level.txt