Metadata-Version: 1.0
Name: contents
Version: 0.1.0
Summary: Put a table of contents in your files!
Home-page: https://github.com/jeanpimentel/contents
Author: Jean Pimentel
Author-email: contato@jeanpimentel.com.br
License: UNKNOWN
Platform: UNKNOWN
